{
  "formatVersion": 1,
  "database": {
    "version": 13,
    "identityHash": "01e9c271b7698a2f4552608edf11a7c4",
    "entities": [
      {
        "tableName": "image",
        "createSql": "CREATE TABLE IF NOT EXISTS `${TABLE_NAME}` (`id` TEXT NOT NULL, `collectionsid` TEXT, `searchQuery` TEXT NOT NULL, `favorite` INTEGER NOT NULL, `promotedAt` TEXT, `color` TEXT, `blurHash` TEXT, `datetime` INTEGER NOT NULL, `lastedit` INTEGER NOT NULL, `width` INTEGER, `height` INTEGER, `description` TEXT, `small` TEXT, `regular` TEXT, `thumb` TEXT, `links` TEXT, `downloads` INTEGER, PRIMARY KEY(`id`))",
        "fields": [
          {
            "fieldPath": "id",
            "columnName": "id",
            "affinity": "TEXT",
            "notNull": true
          },
          {
            "fieldPath": "collectionsid",
            "columnName": "collectionsid",
            "affinity": "TEXT",
            "notNull": false
          },
          {
            "fieldPath": "query",
            "columnName": "searchQuery",
            "affinity": "TEXT",
            "notNull": true
          },
          {
            "fieldPath": "favorite",
            "columnName": "favorite",
            "affinity": "INTEGER",
            "notNull": true
          },
          {
            "fieldPath": "promotedAt",
            "columnName": "promotedAt",
            "affinity": "TEXT",
            "notNull": false
          },
          {
            "fieldPath": "color",
            "columnName": "color",
            "affinity": "TEXT",
            "notNull": false
          },
          {
            "fieldPath": "blurHash",
            "columnName": "blurHash",
            "affinity": "TEXT",
            "notNull": false
          },
          {
            "fieldPath": "dateTime",
            "columnName": "datetime",
            "affinity": "INTEGER",
            "notNull": true
          },
          {
            "fieldPath": "lastEdit",
            "columnName": "lastedit",
            "affinity": "INTEGER",
            "notNull": true
          },
          {
            "fieldPath": "width",
            "columnName": "width",
            "affinity": "INTEGER",
            "notNull": false
          },
          {
            "fieldPath": "height",
            "columnName": "height",
            "affinity": "INTEGER",
            "notNull": false
          },
          {
            "fieldPath": "description",
            "columnName": "description",
            "affinity": "TEXT",
            "notNull": false
          },
          {
            "fieldPath": "smallImageUrl",
            "columnName": "small",
            "affinity": "TEXT",
            "notNull": false
          },
          {
            "fieldPath": "regularImageUrl",
            "columnName": "regular",
            "affinity": "TEXT",
            "notNull": false
          },
          {
            "fieldPath": "thumb",
            "columnName": "thumb",
            "affinity": "TEXT",
            "notNull": false
          },
          {
            "fieldPath": "links",
            "columnName": "links",
            "affinity": "TEXT",
            "notNull": false
          },
          {
            "fieldPath": "downloads",
            "columnName": "downloads",
            "affinity": "INTEGER",
            "notNull": false
          }
        ],
        "primaryKey": {
          "columnNames": [
            "id"
          ],
          "autoGenerate": false
        },
        "indices": [],
        "foreignKeys": []
      },
      {
        "tableName": "collections",
        "createSql": "CREATE TABLE IF NOT EXISTS `${TABLE_NAME}` (`id` TEXT NOT NULL, `title` TEXT, `description` TEXT, `publishedAt` TEXT, `updatedAt` TEXT, `totalPhotos` INTEGER NOT NULL, `links` TEXT, `coverPhoto` TEXT, PRIMARY KEY(`id`))",
        "fields": [
          {
            "fieldPath": "id",
            "columnName": "id",
            "affinity": "TEXT",
            "notNull": true
          },
          {
            "fieldPath": "title",
            "columnName": "title",
            "affinity": "TEXT",
            "notNull": false
          },
          {
            "fieldPath": "description",
            "columnName": "description",
            "affinity": "TEXT",
            "notNull": false
          },
          {
            "fieldPath": "publishedAt",
            "columnName": "publishedAt",
            "affinity": "TEXT",
            "notNull": false
          },
          {
            "fieldPath": "updatedAt",
            "columnName": "updatedAt",
            "affinity": "TEXT",
            "notNull": false
          },
          {
            "fieldPath": "totalPhotos",
            "columnName": "totalPhotos",
            "affinity": "INTEGER",
            "notNull": true
          },
          {
            "fieldPath": "links",
            "columnName": "links",
            "affinity": "TEXT",
            "notNull": false
          },
          {
            "fieldPath": "coverPhoto",
            "columnName": "coverPhoto",
            "affinity": "TEXT",
            "notNull": false
          }
        ],
        "primaryKey": {
          "columnNames": [
            "id"
          ],
          "autoGenerate": false
        },
        "indices": [],
        "foreignKeys": []
      },
      {
        "tableName": "searchkey",
        "createSql": "CREATE TABLE IF NOT EXISTS `${TABLE_NAME}` (`key` TEXT NOT NULL, `datetime` INTEGER NOT NULL, PRIMARY KEY(`key`))",
        "fields": [
          {
            "fieldPath": "key",
            "columnName": "key",
            "affinity": "TEXT",
            "notNull": true
          },
          {
            "fieldPath": "dateTime",
            "columnName": "datetime",
            "affinity": "INTEGER",
            "notNull": true
          }
        ],
        "primaryKey": {
          "columnNames": [
            "key"
          ],
          "autoGenerate": false
        },
        "indices": [],
        "foreignKeys": []
      },
      {
        "tableName": "download_item",
        "createSql": "CREATE TABLE IF NOT EXISTS `${TABLE_NAME}` (`thumb_url` TEXT, `download_url` TEXT, `id` TEXT NOT NULL, `progress` INTEGER NOT NULL, `create_time` INTEGER NOT NULL, `color` INTEGER NOT NULL, `status` INTEGER NOT NULL, `file_path` TEXT, `file_name` TEXT, `width` INTEGER NOT NULL, `height` INTEGER NOT NULL, PRIMARY KEY(`id`))",
        "fields": [
          {
            "fieldPath": "thumbUrl",
            "columnName": "thumb_url",
            "affinity": "TEXT",
            "notNull": false
          },
          {
            "fieldPath": "downloadUrl",
            "columnName": "download_url",
            "affinity": "TEXT",
            "notNull": false
          },
          {
            "fieldPath": "id",
            "columnName": "id",
            "affinity": "TEXT",
            "notNull": true
          },
          {
            "fieldPath": "progress",
            "columnName": "progress",
            "affinity": "INTEGER",
            "notNull": true
          },
          {
            "fieldPath": "createTime",
            "columnName": "create_time",
            "affinity": "INTEGER",
            "notNull": true
          },
          {
            "fieldPath": "color",
            "columnName": "color",
            "affinity": "INTEGER",
            "notNull": true
          },
          {
            "fieldPath": "status",
            "columnName": "status",
            "affinity": "INTEGER",
            "notNull": true
          },
          {
            "fieldPath": "filePath",
            "columnName": "file_path",
            "affinity": "TEXT",
            "notNull": false
          },
          {
            "fieldPath": "fileName",
            "columnName": "file_name",
            "affinity": "TEXT",
            "notNull": false
          },
          {
            "fieldPath": "width",
            "columnName": "width",
            "affinity": "INTEGER",
            "notNull": true
          },
          {
            "fieldPath": "height",
            "columnName": "height",
            "affinity": "INTEGER",
            "notNull": true
          }
        ],
        "primaryKey": {
          "columnNames": [
            "id"
          ],
          "autoGenerate": false
        },
        "indices": [],
        "foreignKeys": []
      }
    ],
    "views": [],
    "setupQueries": [
      "CREATE TABLE IF NOT EXISTS room_master_table (id INTEGER PRIMARY KEY,identity_hash TEXT)",
      "INSERT OR REPLACE INTO room_master_table (id,identity_hash) VALUES(42, '01e9c271b7698a2f4552608edf11a7c4')"
    ]
  }
}